vk/__init__.py
vk/api.py
vk/exceptions.py
vk/session.py
vk/utils.py
vk_paw-3.0.dev1.dist-info/LICENSE
vk_paw-3.0.dev1.dist-info/METADATA
vk_paw-3.0.dev1.dist-info/WHEEL
vk_paw-3.0.dev1.dist-info/top_level.txt
vk_paw-3.0.dev1.dist-info/RECORD
