Metadata-Version: 2.1
Name: vk-paw
Version: 3.0.dev1
Summary: Python vk.com API wrapper
Author-email: Dmitry Voronin <dimka665@gmail.com>
Maintainer-email: Yaroslav Kikel <yaroslav.kikel.06@inbox.ru>
License: MIT
Keywords: vk.com,api,vk,wrappper
Classifier: Development Status :: 5 - Production/Stable
Classifier: Intended Audience :: Developers
Classifier: License :: OSI Approved :: MIT License
Classifier: Operating System :: OS Independent
Classifier: Programming Language :: Python
Classifier: Programming Language :: Python :: 3
Classifier: Programming Language :: Python :: 3 :: Only
Classifier: Programming Language :: Python :: 3.7
Classifier: Programming Language :: Python :: 3.8
Classifier: Programming Language :: Python :: 3.9
Classifier: Programming Language :: Python :: 3.10
Classifier: Programming Language :: Python :: Implementation :: CPython
Classifier: Programming Language :: Python :: Implementation :: PyPy
Classifier: Topic :: Software Development :: Libraries :: Python Modules
License-File: LICENSE
Requires-Dist: requests (~=2.24)
Provides-Extra: docs
Requires-Dist: sphinx (>=4) ; extra == 'docs'
Requires-Dist: sphinx-autobuild (>=2021) ; extra == 'docs'
Provides-Extra: test
Requires-Dist: pytest (>=6) ; extra == 'test'
Requires-Dist: pytest-cov (>=2.7) ; extra == 'test'
